{
  "obsidian-git:backup-and-close": [
    {
      "modifiers": [
        "Mod"
      ],
      "key": "Q"
    }
  ],
  "obsidian-git:push": [
    {
      "modifiers": [
        "Mod",
        "Shift"
      ],
      "key": "Q"
    }
  ],
  "file-explorer:open": [
    {
      "modifiers": [
        "Mod",
        "Shift"
      ],
      "key": "E"
    }
  ],
  "open-with-default-app:show": [
    {
      "modifiers": [
        "Alt",
        "Mod",
        "Shift"
      ],
      "key": "E"
    }
  ],
  "app:toggle-left-sidebar": [
    {
      "modifiers": [
        "Mod"
      ],
      "key": "B"
    }
  ],
  "editor:toggle-bold": [],
  "editor:toggle-italics": [],
  "workspace:goto-tab-1": [],
  "workspace:goto-tab-2": [],
  "workspace:goto-tab-3": [],
  "workspace:goto-tab-4": [],
  "workspace:goto-tab-5": [],
  "workspace:goto-tab-6": [],
  "workspace:goto-tab-7": [],
  "workspace:goto-tab-8": [],
  "app:toggle-right-sidebar": [
    {
      "modifiers": [
        "Alt",
        "Mod"
      ],
      "key": "B"
    }
  ],
  "markdown:toggle-preview": [],
  "editor:toggle-source": [
    {
      "modifiers": [
        "Mod"
      ],
      "key": "E"
    }
  ],
  "app:go-back": [
    {
      "modifiers": [
        "Mod",
        "Alt"
      ],
      "key": "ArrowLeft"
    },
    {
      "modifiers": [
        "Alt"
      ],
      "key": "ArrowLeft"
    }
  ],
  "app:go-forward": [
    {
      "modifiers": [
        "Mod",
        "Alt"
      ],
      "key": "ArrowRight"
    },
    {
      "modifiers": [
        "Alt"
      ],
      "key": "ArrowRight"
    }
  ],
  "editor:focus-right": [
    {
      "modifiers": [
        "Mod",
        "Shift"
      ],
      "key": "ArrowRight"
    }
  ],
  "editor:focus-bottom": [
    {
      "modifiers": [
        "Mod",
        "Shift"
      ],
      "key": "ArrowDown"
    }
  ],
  "editor:focus-left": [
    {
      "modifiers": [
        "Mod",
        "Shift"
      ],
      "key": "ArrowLeft"
    }
  ],
  "editor:focus-top": [
    {
      "modifiers": [
        "Mod",
        "Shift"
      ],
      "key": "ArrowUp"
    }
  ],
  "obsidian-git:open-git-view": [
    {
      "modifiers": [
        "Mod",
        "Shift"
      ],
      "key": "G"
    }
  ],
  "outline:open": [
    {
      "modifiers": [
        "Mod",
        "Shift"
      ],
      "key": "O"
    }
  ],
  "editor:swap-line-up": [
    {
      "modifiers": [
        "Alt"
      ],
      "key": "ArrowUp"
    }
  ],
  "editor:swap-line-down": [
    {
      "modifiers": [
        "Alt"
      ],
      "key": "ArrowDown"
    }
  ],
  "editor:open-link-in-new-leaf": [],
  "editor:toggle-fold": [
    {
      "modifiers": [
        "Mod"
      ],
      "key": "Enter"
    }
  ]
}